ezmsg/rerun/__init__.py
ezmsg_rerun-0.1.0.dist-info/METADATA
ezmsg_rerun-0.1.0.dist-info/WHEEL
ezmsg_rerun-0.1.0.dist-info/licenses/LICENSE.txt
ezmsg_rerun-0.1.0.dist-info/RECORD
