Metadata-Version: 2.3
Name: ezmsg-rerun
Version: 0.1.0
Summary: ezmsg extension for rerun visualization.
Author-email: Preston Peranich <pperanich@gmail.com>
License: MIT License
License-File: LICENSE.txt
Requires-Python: >=3.9
Requires-Dist: ezmsg>=3.4.0
Requires-Dist: rerun-sdk>=0.18.0
Provides-Extra: test
Requires-Dist: pytest>=8.3.2; extra == 'test'
